inventree_part_templates/__init__.py
inventree_part_templates/part_templates.yaml
inventree_part_templates/part_templates_plugin.py
inventree_part_templates/version.py
inventree_part_templates/example_labels/inventree-label-part-16mm.html
inventree_part_templates/example_labels/inventree-label-part-29mm.html
inventree_part_templates/example_labels/inventree-label-part-smdbox.html
inventree_part_templates/templates/part_templates/part_detail_panel.html
inventree_part_templates/templatetags/__init__.py
inventree_part_templates/templatetags/part_templates.py
inventree_part_templates-0.3.1.dist-info/LICENSE
inventree_part_templates-0.3.1.dist-info/METADATA
inventree_part_templates-0.3.1.dist-info/WHEEL
inventree_part_templates-0.3.1.dist-info/entry_points.txt
inventree_part_templates-0.3.1.dist-info/top_level.txt
inventree_part_templates-0.3.1.dist-info/RECORD
