Metadata-Version: 2.1
Name: inventree-part-templates
Version: 0.3.1
Summary: InvenTree plugin that extends reporting with customizable part category templates
Home-page: https://github.com/cmidgley/inventree-part-templates
Author: Chris Midgley
Author-email: chris@koose.com
License: MIT
Keywords: inventree inventreeplugins plugins label report part category print template
Requires-Python: >=3.9
License-File: LICENSE
